odoo8_addon_l10n_br_account_payment_mode-8.0.1.0.0.99.dev29-py2.7-nspkg.pth
odoo8_addon_l10n_br_account_payment_mode-8.0.1.0.0.99.dev29.dist-info/METADATA
odoo8_addon_l10n_br_account_payment_mode-8.0.1.0.0.99.dev29.dist-info/RECORD
odoo8_addon_l10n_br_account_payment_mode-8.0.1.0.0.99.dev29.dist-info/WHEEL
odoo8_addon_l10n_br_account_payment_mode-8.0.1.0.0.99.dev29.dist-info/namespace_packages.txt
odoo8_addon_l10n_br_account_payment_mode-8.0.1.0.0.99.dev29.dist-info/top_level.txt
odoo_addons/l10n_br_account_payment_mode/README.rst
odoo_addons/l10n_br_account_payment_mode/__init__.py
odoo_addons/l10n_br_account_payment_mode/__openerp__.py
odoo_addons/l10n_br_account_payment_mode/demo/payment_demo.xml
odoo_addons/l10n_br_account_payment_mode/models/__init__.py
odoo_addons/l10n_br_account_payment_mode/models/payment_mode.py
odoo_addons/l10n_br_account_payment_mode/models/res_partner_bank.py
odoo_addons/l10n_br_account_payment_mode/static/description/icon.png
odoo_addons/l10n_br_account_payment_mode/views/account_invoice_view.xml
odoo_addons/l10n_br_account_payment_mode/views/payment_mode_view.xml
