Metadata-Version: 2.1
Name: odoo8-addon-l10n-br-account-payment-mode
Version: 8.0.1.0.0.99.dev29
Summary: Odoo Brazil Payments Mode
Home-page: https://odoo-community.org/
Author: KMEE, Odoo Community Association (OCA)
Author-email: support@odoo-community.org
License: AGPL-3
Platform: UNKNOWN
Classifier: Programming Language :: Python
Classifier: Framework :: Odoo
Classifier: License :: OSI Approved :: GNU Affero General Public License v3
Requires-Python: ~=2.7
Requires-Dist: odoo8-addon-account-due-list-payment-mode
Requires-Dist: odoo8-addon-l10n-br-account-banking-payment
Requires-Dist: odoo8-addon-l10n-br-account-product
Requires-Dist: odoo8-addon-l10n-br-data-base
Requires-Dist: odoo (<9.0a,>=8.0a)
